spotflow_device-2.1.1.dist-info/METADATA
spotflow_device-2.1.1.dist-info/WHEEL
spotflow_device/__init__.py
spotflow_device/__init__.pyi
spotflow_device/py.typed
spotflow_device/spotflow_device.abi3.so
spotflow_device-2.1.1.dist-info/RECORD
