Metadata-Version: 2.4
Name: spotflow_device
Version: 2.1.1
Classifier: Programming Language :: Rust
Classifier: Programming Language :: Python :: Implementation :: CPython
Classifier: Programming Language :: Python :: Implementation :: PyPy
Summary: Device SDK for Spotflow IoT Platform
Keywords: spotflow,iot,device,sdk
Author-email: Spotflow <support@spotflow.io>
Requires-Python: >=3.7
Project-URL: Homepage, https://iot.spotflow.io/platform
Project-URL: Documentation, https://docs.iot.spotflow.io/device-sdk/python/
Project-URL: Changelog, https://github.com/spotflow-io/iot-platform-device-sdk/blob/main/spotflow-py/CHANGELOG.md
